[
    {
      "id": "1",
      "body": "This tastes good!",
      "stars": 5,
      "username": "Sarah",
      "userId": "1",
      "parentId": null,
      "createdAt": "2022-10-16"
    },
    {
      "id": "2",
      "body": "It was too difficult to make.",
      "stars": 2,
      "username": "Mark",
      "userId": "2",
      "parentId": null,
      "createdAt": "2022-10-16"
    },
    {
      "id": "3",
      "body": "Not a bad meal, but too heavy.",
      "stars": 4,
      "username": "John",
      "userId": "2",
      "parentId": "1",
      "createdAt": "2022-10-16"
    },
    {
      "id": "4",
      "body": "I enjoyed it, but not my kids.",
      "stars": 3,
      "username": "Alex",
      "userId": "2",
      "parentId": "2",
      "createdAt": "2022-10-16"
    }
]
